graphviz/__init__.py
graphviz/_compat.py
graphviz/_defaults.py
graphviz/_tools.py
graphviz/base.py
graphviz/copying.py
graphviz/dot.py
graphviz/encoding.py
graphviz/exceptions.py
graphviz/graphs.py
graphviz/jupyter_integration.py
graphviz/piping.py
graphviz/quoting.py
graphviz/rendering.py
graphviz/saving.py
graphviz/sources.py
graphviz/unflattening.py
graphviz/backend/__init__.py
graphviz/backend/dot_command.py
graphviz/backend/execute.py
graphviz/backend/mixins.py
graphviz/backend/piping.py
graphviz/backend/rendering.py
graphviz/backend/unflattening.py
graphviz/backend/upstream_version.py
graphviz/backend/viewing.py
graphviz/parameters/__init__.py
graphviz/parameters/base.py
graphviz/parameters/engines.py
graphviz/parameters/formats.py
graphviz/parameters/formatters.py
graphviz/parameters/mixins.py
graphviz/parameters/renderers.py
graphviz-0.20.2.dist-info/LICENSE.txt
graphviz-0.20.2.dist-info/METADATA
graphviz-0.20.2.dist-info/WHEEL
graphviz-0.20.2.dist-info/top_level.txt
graphviz-0.20.2.dist-info/RECORD
