Metadata-Version: 2.1
Name: graphviz
Version: 0.20.2
Summary: Simple Python interface for Graphviz
Home-page: https://github.com/xflr6/graphviz
Author: Sebastian Bank
Author-email: sebastian.bank@uni-leipzig.de
License: MIT
Project-URL: Documentation, https://graphviz.readthedocs.io
Project-URL: Changelog, https://graphviz.readthedocs.io/en/latest/changelog.html
Project-URL: Issue Tracker, https://github.com/xflr6/graphviz/issues
Project-URL: CI, https://github.com/xflr6/graphviz/actions
Project-URL: Coverage, https://codecov.io/gh/xflr6/graphviz
Keywords: graph visualization dot render
Platform: any
Classifier: Development Status :: 4 - Beta
Classifier: Intended Audience :: Developers
Classifier: Intended Audience :: Science/Research
Classifier: License :: OSI Approved :: MIT License
Classifier: Operating System :: OS Independent
Classifier: Programming Language :: Python :: 3
Classifier: Programming Language :: Python :: 3.8
Classifier: Programming Language :: Python :: 3.9
Classifier: Programming Language :: Python :: 3.10
Classifier: Programming Language :: Python :: 3.11
Classifier: Programming Language :: Python :: 3.12
Classifier: Topic :: Scientific/Engineering :: Visualization
Requires-Python: >=3.8
License-File: LICENSE.txt
Provides-Extra: dev
Requires-Dist: tox>=3; extra == "dev"
Requires-Dist: flake8; extra == "dev"
Requires-Dist: pep8-naming; extra == "dev"
Requires-Dist: wheel; extra == "dev"
Requires-Dist: twine; extra == "dev"
Provides-Extra: test
Requires-Dist: pytest<8.1,>=7; extra == "test"
Requires-Dist: pytest-mock>=3; extra == "test"
Requires-Dist: pytest-cov; extra == "test"
Requires-Dist: coverage; extra == "test"
Provides-Extra: docs
Requires-Dist: sphinx<7,>=5; extra == "docs"
Requires-Dist: sphinx-autodoc-typehints; extra == "docs"
Requires-Dist: sphinx-rtd-theme; extra == "docs"
